AUTHORS.rst
HISTORY.rst
MANIFEST.in
README.rst
dev-requirements.txt
requirements.txt
setup.py
purkinje_messages/__init__.py
purkinje_messages/message.py
purkinje_messages.egg-info/PKG-INFO
purkinje_messages.egg-info/SOURCES.txt
purkinje_messages.egg-info/dependency_links.txt
purkinje_messages.egg-info/not-zip-safe
purkinje_messages.egg-info/requires.txt
purkinje_messages.egg-info/top_level.txt
tests/__init__.py
tests/message_test.py