Metadata-Version: 1.1
Name: purkinje-messages
Version: 0.1.3
Summary: message definitions for purkinje test runner
Home-page: biskup-software.de
Author: Bernhard (Bernd) Biskup
Author-email: bbiskup@gmx.de
License: The MIT License (MIT)
Keywords: purkinje pytest testrunner websockets
Platform: UNKNOWN
Classifier: Development Status :: 2 - Pre-Alpha
Classifier: Environment :: Console
Classifier: Environment :: Web Environment
Classifier: Intended Audience :: Developers
Classifier: Topic :: Software Development :: Testing
Classifier: License :: OSI Approved :: MIT License
Classifier: Programming Language :: Python :: 2.7
